fastrict-1.0.1.dist-info/licenses/LICENSE
tests/__init__.py
tests/test_basic.py
fastrict-1.0.1.dist-info/METADATA
fastrict-1.0.1.dist-info/WHEEL
fastrict-1.0.1.dist-info/top_level.txt
fastrict-1.0.1.dist-info/RECORD
