Metadata-Version: 2.4
Name: fastrict
Version: 1.0.1
Summary: A comprehensive rate limiting system for FastAPI with Redis backend
Home-page: https://github.com/msameim181/fastrict
Author: Mohammad Mahdi Samei
Author-email: Mohammad Mahdi Samei <9259samei@gmail.com>
License: MIT
Project-URL: Homepage, https://github.com/msameim181/fastrict
Project-URL: Bug Reports, https://github.com/msameim181/fastrict/issues
Project-URL: Source, https://github.com/msameim181/fastrict
Project-URL: Documentation, https://fastrict.readthedocs.io/
Keywords: fastapi,rate limiting,redis,middleware,decorator,throttle
Classifier: Development Status :: 5 - Production/Stable
Classifier: Intended Audience :: Developers
Classifier: License :: OSI Approved :: MIT License
Classifier: Operating System :: OS Independent
Classifier: Programming Language :: Python :: 3
Classifier: Programming Language :: Python :: 3.8
Classifier: Programming Language :: Python :: 3.9
Classifier: Programming Language :: Python :: 3.10
Classifier: Programming Language :: Python :: 3.11
Classifier: Programming Language :: Python :: 3.12
Classifier: Framework :: FastAPI
Classifier: Topic :: Internet :: WWW/HTTP :: HTTP Servers
Classifier: Topic :: Software Development :: Libraries :: Python Modules
Classifier: Topic :: System :: Systems Administration
Requires-Python: >=3.8
License-File: LICENSE
Requires-Dist: fastapi>=0.68.0
Requires-Dist: redis>=4.0.0
Requires-Dist: pydantic>=1.8.0
Requires-Dist: starlette>=0.14.0
Provides-Extra: dev
Requires-Dist: pytest>=6.0; extra == "dev"
Requires-Dist: pytest-asyncio>=0.18.0; extra == "dev"
Requires-Dist: pytest-cov>=2.0; extra == "dev"
Requires-Dist: black>=22.0; extra == "dev"
Requires-Dist: flake8>=4.0; extra == "dev"
Requires-Dist: mypy>=0.950; extra == "dev"
Requires-Dist: pre-commit>=2.0; extra == "dev"
Provides-Extra: docs
Requires-Dist: mkdocs>=1.4; extra == "docs"
Requires-Dist: mkdocs-material>=8.0; extra == "docs"
Requires-Dist: mkdocstrings[python]>=0.19; extra == "docs"
Dynamic: author
Dynamic: home-page
Dynamic: license-file
Dynamic: requires-python
